pycwr/__init__.py
pycwr/GraphicalInterface/RadarInterface.py
pycwr/GraphicalInterface/RadarUI.py
pycwr/GraphicalInterface/__init__.py
pycwr/GraphicalInterface/icons.py
pycwr/GraphicalInterface/station_info.py
pycwr/configure/__init__.py
pycwr/configure/config.py
pycwr/configure/default_config.py
pycwr/configure/location_config.py
pycwr/configure/pyart_config.py
pycwr/configure/pyart_default_config.py
pycwr/configure/pyart_lazydict.py
pycwr/core/NRadar.py
pycwr/core/PyartRadar.py
pycwr/core/RadarGrid.py
pycwr/core/RadarGridC.cpython-310-darwin.so
pycwr/core/RadarGridC.pyx
pycwr/core/__init__.py
pycwr/core/transforms.py
pycwr/data/CHN_pronvices.dbf
pycwr/data/CHN_pronvices.prj
pycwr/data/CHN_pronvices.sbn
pycwr/data/CHN_pronvices.sbx
pycwr/data/CHN_pronvices.shp
pycwr/data/CHN_pronvices.shx
pycwr/data/beta_function_parameters.nc
pycwr/data/default_opendir.json
pycwr/data/radar_info.json
pycwr/draw/RadarPlot.py
pycwr/draw/SingleRadarPlot.py
pycwr/draw/SingleRadarPlotMap.py
pycwr/draw/VerticalSectionPlot.py
pycwr/draw/__init__.py
pycwr/draw/colormap/__init__.py
pycwr/draw/colormap/_cm.py
pycwr/draw/colormap/_cm_colorblind.py
pycwr/draw/colormap/balance-rgb.txt
pycwr/draw/colormap/cm.py
pycwr/draw/colormap/cm_colorblind.py
pycwr/interp/RadarInterp.py
pycwr/interp/__init__.py
pycwr/io/CCFile.py
pycwr/io/PAFile.py
pycwr/io/SABFile.py
pycwr/io/SCFile.py
pycwr/io/WSR98DFile.py
pycwr/io/__init__.py
pycwr/io/util.py
pycwr/io/BaseDataProtocol/CCProtocol.py
pycwr/io/BaseDataProtocol/PAProtocol.py
pycwr/io/BaseDataProtocol/SABProtocol.py
pycwr/io/BaseDataProtocol/SCProtocol.py
pycwr/io/BaseDataProtocol/WSR98DProtocol.py
pycwr/io/BaseDataProtocol/__init__.py
pycwr/qc/__init__.py
pycwr/qc/attenuation.py
pycwr/retrieve/HID.py
pycwr/retrieve/WindField.py
pycwr/retrieve/__init__.py
pycwr-0.4.0.dist-info/LICENSE.txt
pycwr-0.4.0.dist-info/METADATA
pycwr-0.4.0.dist-info/WHEEL
pycwr-0.4.0.dist-info/top_level.txt
pycwr-0.4.0.dist-info/RECORD
